jumpy.py
brax_jumpy-0.1.0.dist-info/METADATA
brax_jumpy-0.1.0.dist-info/WHEEL
brax_jumpy-0.1.0.dist-info/licenses/LICENSE
brax_jumpy-0.1.0.dist-info/RECORD
