Metadata-Version: 2.1
Name: brax-jumpy
Version: 0.1.0
Summary: Common backend for JAX or numpy.
Project-URL: Homepage, https://farama.org/
Project-URL: Repository, https://github.com/Farama-Foundation/Jumpy
Author-email: Farama Foundation <jkterry@farama.org>
License: Copyright 2022 Farama Foundation
Classifier: Development Status :: 4 - Beta
Classifier: Intended Audience :: Developers
Classifier: Intended Audience :: Science/Research
Classifier: License :: OSI Approved :: Apache Software License
Classifier: Programming Language :: Python
Classifier: Topic :: Scientific/Engineering :: Artificial Intelligence
Requires-Dist: jax
Requires-Dist: jaxlib
Requires-Dist: numpy
Provides-Extra: dev
Requires-Dist: pytest; extra == 'dev'
